wp21_train/__init__.py
wp21_train/project.py
wp21_train/bookkeeping/__init__.py
wp21_train/bookkeeping/paths.py
wp21_train/bookkeeping/keys/__init__.py
wp21_train/bookkeeping/keys/cluster_keys.py
wp21_train/bookkeeping/keys/gep_keys.py
wp21_train/bookkeeping/keys/keys.py
wp21_train/bookkeeping/keys/ml_keys.py
wp21_train/callbacks/__init__.py
wp21_train/callbacks/base_callback.py
wp21_train/data/__init__.py
wp21_train/data/data.py
wp21_train/parser/__init__.py
wp21_train/parser/aie_parser.py
wp21_train/parser/athena_parser.py
wp21_train/parser/hls_parser.py
wp21_train/physics/__init__.py
wp21_train/physics/matching.py
wp21_train/physics/performance.py
wp21_train/physics/clustering/__init__.py
wp21_train/physics/clustering/cluster_discriminants.py
wp21_train/physics/clustering/clustering.py
wp21_train/physics/clustering/clustering_config.py
wp21_train/physics/clustering/diagnostics.py
wp21_train/physics/clustering/backends/__init__.py
wp21_train/physics/clustering/backends/clustering_cpp_openmp_impl.cpp
wp21_train/physics/clustering/backends/clustering_wrap.py
wp21_train/physics/plotting/__init__.py
wp21_train/physics/plotting/turnon.py
wp21_train/physics/trigger/__init__.py
wp21_train/physics/trigger/roi_trigger.py
wp21_train/physics/trigger/trigger.py
wp21_train/physics/trigger/trigger_scan.py
wp21_train/physics/trigger/baseline/__init__.py
wp21_train/physics/trigger/baseline/l0calo_efex_tau.py
wp21_train/savers/__init__.py
wp21_train/savers/adapter.py
wp21_train/savers/json_adapter.py
wp21_train/savers/pickle_adapter.py
wp21_train/savers/root_adapter.py
wp21_train/savers/yml_adapter.py
wp21_train/training/__init__.py
wp21_train/training/evaluator.py
wp21_train/training/tuner.py
wp21_train/training/searchers/__init__.py
wp21_train/training/searchers/base_search.py
wp21_train/training/searchers/grid_search.py
wp21_train/training/searchers/random_search.py
wp21_train/training/trainers/__init__.py
wp21_train/training/trainers/base.py
wp21_train-0.7.9.dist-info/METADATA
wp21_train-0.7.9.dist-info/WHEEL
wp21_train-0.7.9.dist-info/top_level.txt
wp21_train-0.7.9.dist-info/RECORD
