Metadata-Version: 2.4
Name: wp21_train
Version: 0.7.9
Summary: Framework that provides tools allowing for monitoring, training and evaluating ML models
Home-page: https://gitlab.cern.ch/atlas-nextgen-wp21/wp21_training_framework.git
Author: ATLAS NextGen WP2.1
Author-email: ngtwp21@cern.ch
Classifier: Programming Language :: Python :: 3
Classifier: Programming Language :: Python :: 3 :: Only
Classifier: License :: OSI Approved :: MIT License
Classifier: Operating System :: OS Independent
Requires-Python: >=3.10
Requires-Dist: numpy<2.0,>=1.21
Requires-Dist: PyYAML<7.0,>=6.0
Requires-Dist: uproot<6.0,>=5.0
Requires-Dist: awkward<3.0,>=2.5
Requires-Dist: lz4<5.0,>=4.3
Requires-Dist: xxhash<4.0,>=3.4
Requires-Dist: tqdm>=4.67.1
Requires-Dist: pybind11>=3.0.1
Requires-Dist: vector>=1.7.0
Requires-Dist: pyarrow>=18.0.0
Requires-Dist: hgq==0.2.6
Provides-Extra: torch
Requires-Dist: torch>=2.1; extra == "torch"
Provides-Extra: tensorflow
Requires-Dist: tensorflow>=2.13; extra == "tensorflow"
Provides-Extra: tf-tools
Requires-Dist: tf2onnx>=1.14; extra == "tf-tools"
Provides-Extra: dev
Requires-Dist: pytest>=7.0; extra == "dev"
Requires-Dist: pytest-cov>=4.0; extra == "dev"
Requires-Dist: ruff>=0.4; extra == "dev"
Requires-Dist: mypy>=1.5; extra == "dev"
Dynamic: author
Dynamic: author-email
Dynamic: classifier
Dynamic: description
Dynamic: description-content-type
Dynamic: home-page
Dynamic: provides-extra
Dynamic: requires-dist
Dynamic: requires-python
Dynamic: summary
